MANIFEST.in
README.md
setup.py
practools/active_obj.py
practools/actor.py
practools/box.py
practools/camera.py
practools/core.py
practools/cube.py
practools/cylinder.py
practools/editor.py
practools/placer.py
practools/printer3d.py
practools/robot.py
practools/scene.py
practools/stacker.py
practools/viewer.py
practools/workflow.py
practools.egg-info/PKG-INFO
practools.egg-info/SOURCES.txt
practools.egg-info/dependency_links.txt
practools.egg-info/requires.txt
practools.egg-info/top_level.txt
practools/end_effector/__init__.py
practools/end_effector/gripper.py
practools/end_effector/suction.py